greenland/base/__init__.py
greenland/base/bin/__init__.py
greenland/base/bin/greenland.py
greenland/base/bin/pytest-bist.ini
greenland/base/bin/runtime.py
greenland5_base-0.0.4.dist-info/AUTHORS
greenland5_base-0.0.4.dist-info/LICENSE
greenland5_base-0.0.4.dist-info/METADATA
greenland5_base-0.0.4.dist-info/WHEEL
greenland5_base-0.0.4.dist-info/entry_points.txt
greenland5_base-0.0.4.dist-info/top_level.txt
greenland5_base-0.0.4.dist-info/RECORD
