Metadata-Version: 2.1
Name: greenland5-base
Version: 0.0.4
Summary: Base package for all greenland5 packages containing a command line interface to run built-in self tests
Home-page: https://gitlab.com/m-e-leypold/greenland5-base
Author: M E Leypold
Author-email: greenland5-sk01mq04ym43pr@m-e-leypold.de
License: GPLv3
Platform: UNKNOWN
Classifier: Development Status :: 3 - Alpha
Classifier: Environment :: Console
Classifier: Intended Audience :: Developers
Classifier: License :: OSI Approved :: GNU General Public License v3 (GPLv3)
Classifier: Operating System :: POSIX
Classifier: Programming Language :: Python
Requires-Python: >=3.7
License-File: LICENSE
License-File: AUTHORS
Requires-Dist: docopt
